seqio/__init__.py
seqio/beam_utils.py
seqio/beam_utils_test.py
seqio/dataset_providers.py
seqio/dataset_providers_helpers.py
seqio/dataset_providers_test.py
seqio/evaluation.py
seqio/evaluation_test.py
seqio/experimental.py
seqio/experimental_test.py
seqio/feature_converters.py
seqio/feature_converters_test.py
seqio/helpers.py
seqio/helpers_test.py
seqio/loggers.py
seqio/loggers_test.py
seqio/metrics.py
seqio/metrics_test.py
seqio/preprocessors.py
seqio/preprocessors_test.py
seqio/sharded_evaluation_test.py
seqio/task_registry_provenance_tracking.py
seqio/task_registry_provenance_tracking_test.py
seqio/test_utils.py
seqio/test_utils_test.py
seqio/utils.py
seqio/utils_test.py
seqio/version.py
seqio/vocabularies.py
seqio/vocabularies_test.py
seqio/scripts/__init__.py
seqio/scripts/cache_tasks_main.py
seqio/scripts/cache_tasks_test.py
seqio/scripts/inspect_tasks_main.py
seqio/scripts/registration_provenance_main.py
seqio/scripts/registration_provenance_test.py
seqio/test_data/bertwordpiece/vocab.txt
seqio/test_data/cached_plaintext_task/COMPLETED
seqio/test_data/cached_plaintext_task/info.train.json
seqio/test_data/cached_plaintext_task/stats.train.json
seqio/test_data/cached_task/COMPLETED
seqio/test_data/cached_task/info.train.json
seqio/test_data/cached_task/info.validation.json
seqio/test_data/cached_task/stats.train.json
seqio/test_data/cached_task/stats.validation.json
seqio/test_data/cached_task_with_provenance/COMPLETED
seqio/test_data/cached_task_with_provenance/info.train.json
seqio/test_data/cached_task_with_provenance/info.validation.json
seqio/test_data/cached_task_with_provenance/stats.train.json
seqio/test_data/cached_task_with_provenance/stats.validation.json
seqio/test_data/cached_untokenized_ndfeatures_task/COMPLETED
seqio/test_data/cached_untokenized_ndfeatures_task/info.train.json
seqio/test_data/cached_untokenized_ndfeatures_task/info.validation.json
seqio/test_data/cached_untokenized_ndfeatures_task/stats.train.json
seqio_nightly-0.0.18.dev20250227.dist-info/LICENSE
seqio_nightly-0.0.18.dev20250227.dist-info/METADATA
seqio_nightly-0.0.18.dev20250227.dist-info/WHEEL
seqio_nightly-0.0.18.dev20250227.dist-info/entry_points.txt
seqio_nightly-0.0.18.dev20250227.dist-info/top_level.txt
seqio_nightly-0.0.18.dev20250227.dist-info/RECORD
