Metadata-Version: 2.2
Name: seqio-nightly
Version: 0.0.18.dev20250227
Summary: SeqIO: Task-based datasets, preprocessing, and evaluation for sequence models.
Home-page: https://github.com/google/seqio/tree/nightly
Author: Google Inc.
Author-email: no-reply@google.com
License: Apache 2.0
Keywords: sequence preprocessing nlp machinelearning
Classifier: Development Status :: 4 - Beta
Classifier: Intended Audience :: Developers
Classifier: Intended Audience :: Science/Research
Classifier: License :: OSI Approved :: Apache Software License
Classifier: Topic :: Scientific/Engineering :: Artificial Intelligence
License-File: LICENSE
Requires-Dist: absl-py
Requires-Dist: clu
Requires-Dist: editdistance
Requires-Dist: jax
Requires-Dist: jaxlib
Requires-Dist: numpy
Requires-Dist: packaging
Requires-Dist: pyglove
Requires-Dist: sentencepiece>=0.2
Requires-Dist: tensorflow-text
Requires-Dist: tfds-nightly==4.9.2.dev202308090034
Provides-Extra: gcp
Requires-Dist: gevent; extra == "gcp"
Requires-Dist: google-api-python-client; extra == "gcp"
Requires-Dist: google-compute-engine; extra == "gcp"
Requires-Dist: google-cloud-storage; extra == "gcp"
Requires-Dist: oauth2client; extra == "gcp"
Provides-Extra: cache-tasks
Requires-Dist: apache-beam; extra == "cache-tasks"
Provides-Extra: test
Requires-Dist: pytest; extra == "test"
Dynamic: author
Dynamic: author-email
Dynamic: classifier
Dynamic: description
Dynamic: description-content-type
Dynamic: home-page
Dynamic: keywords
Dynamic: license
Dynamic: provides-extra
Dynamic: requires-dist
Dynamic: summary
